LICENSE.txt
MANIFEST.in
README.md
setup.cfg
setup.py
contrib/dlm_engine_cli
dlm_engine_cli/__init__.py
dlmenginecli.egg-info/PKG-INFO
dlmenginecli.egg-info/SOURCES.txt
dlmenginecli.egg-info/dependency_links.txt
dlmenginecli.egg-info/requires.txt
dlmenginecli.egg-info/top_level.txt