Metadata-Version: 1.1
Name: dlmenginecli
Version: 0.0.1
Summary: DlmEngine, distributed lock implementation on top of MongoDB and Redis
Home-page: https://github.com/schlitzered/DLMEngineCLI
Author: schlitzer
Author-email: stephan.schultchen@gmail.com
License: MIT
Keywords: dlm,distributes lock manager engine cli
Platform: posix
Classifier: License :: OSI Approved :: MIT License
Classifier: Programming Language :: Python :: 3
